healdata_utils/__init__.py
healdata_utils/cli.py
healdata_utils/config.py
healdata_utils/conversion.py
healdata_utils/io.py
healdata_utils/utils.py
healdata_utils/mappings/__init__.py
healdata_utils/mappings/names.py
healdata_utils/mappings/values.py
healdata_utils/mappings/versions.py
healdata_utils/schemas/__init__.py
healdata_utils/schemas/csv.py
healdata_utils/schemas/json.py
healdata_utils/schemas/redcap.py
healdata_utils/transforms/__init__.py
healdata_utils/transforms/csvdata/__init__.py
healdata_utils/transforms/csvdata/conversion.py
healdata_utils/transforms/csvdatadict/__init__.py
healdata_utils/transforms/csvdatadict/conversion.py
healdata_utils/transforms/excel/conversion.py
healdata_utils/transforms/frictionless/__init__.py
healdata_utils/transforms/frictionless/conversion.py
healdata_utils/transforms/jsontemplate/__init__.py
healdata_utils/transforms/jsontemplate/conversion.py
healdata_utils/transforms/readstat/__init__.py
healdata_utils/transforms/readstat/conversion.py
healdata_utils/transforms/redcapcsv/conversion.py
healdata_utils/transforms/redcapcsv/headers.py
healdata_utils/transforms/redcapcsv/mappings.py
healdata_utils/transforms/sas/__init__.py
healdata_utils/transforms/sas/conversion.py
healdata_utils/transforms/spss/__init__.py
healdata_utils/transforms/spss/conversion.py
healdata_utils/transforms/stata/__init__.py
healdata_utils/transforms/stata/conversion.py
healdata_utils/types/__init__.py
healdata_utils/types/typesets.py
healdata_utils/validators/__init__.py
healdata_utils/validators/frictionless.py
healdata_utils/validators/jsonschema.py
healdata_utils/validators/validate.py
healdata_utils-0.6.0.dist-info/METADATA
healdata_utils-0.6.0.dist-info/WHEEL
healdata_utils-0.6.0.dist-info/entry_points.txt
healdata_utils-0.6.0.dist-info/top_level.txt
healdata_utils-0.6.0.dist-info/RECORD
