Metadata-Version: 2.1
Name: healdata_utils
Version: 0.6.0
Summary: Data packaging tools for the HEAL data ecosystem
Home-page: https://github.com/norc-heal/healdata-utils
Author: Michael Kranz
Author-email: kranz-michael@norc.org
Requires-Dist: petl ==1.7.12
Requires-Dist: jsonschema >=4.17.3
Requires-Dist: PyYaml >=6.0
Requires-Dist: pandas >=1.4
Requires-Dist: pyreadstat >=1.2.0
Requires-Dist: charset-normalizer >=2.1
Requires-Dist: visions >=0.7.5
Requires-Dist: click >=8.1.3
Requires-Dist: python-slugify
Requires-Dist: openpyxl
